turbine_design/__init__.py
turbine_design/compflow_native.py
turbine_design/Data/1D_phi_data_1 copy.csv
turbine_design/Data/1D_phi_data_1.csv
turbine_design/Data/2D_phi_psi_data_1.csv
turbine_design/Data/2D_phi_psi_data_2.csv
turbine_design/Data/2D_phi_psi_data_3.csv
turbine_design/Data/2D_phi_psi_data_4.csv
turbine_design/Data/4D_data_1.csv
turbine_design/Data/4D_data_10.csv
turbine_design/Data/4D_data_2.csv
turbine_design/Data/4D_data_3.csv
turbine_design/Data/4D_data_4.csv
turbine_design/Data/4D_data_5.csv
turbine_design/Data/4D_data_6.csv
turbine_design/Data/4D_data_7.csv
turbine_design/Data/4D_data_8.csv
turbine_design/Data/4D_data_9.csv
turbine_design/Data/5D_turbine_data_1.csv
turbine_design/Data/5D_turbine_data_10.csv
turbine_design/Data/5D_turbine_data_2.csv
turbine_design/Data/5D_turbine_data_3.csv
turbine_design/Data/5D_turbine_data_4.csv
turbine_design/Data/5D_turbine_data_5.csv
turbine_design/Data/5D_turbine_data_6.csv
turbine_design/Data/5D_turbine_data_7.csv
turbine_design/Data/5D_turbine_data_8.csv
turbine_design/Data/5D_turbine_data_9.csv
turbine_design/Data/Co_variation.csv
turbine_design/Data/Co_variation_2.csv
turbine_design/Data/data_F.csv
turbine_design/Data/Lambda_1D.csv
turbine_design/Data/Lambda_1D_results_2.csv
turbine_design/Data/test543.csv
turbine_design/Data/turbine_data.csv
turbine_design/data_tools.py
turbine_design/extra_geom.py
turbine_design/get_shape.py
turbine_design/Models/Al1_model_phi_psi_M2_Co/Al1_model_phi_psi_M2_Co.joblib
turbine_design/Models/Al1_model_phi_psi_M2_Co/Al1_model_phi_psi_M2_Co_output_variable.txt
turbine_design/Models/Al1_model_phi_psi_M2_Co/Al1_model_phi_psi_M2_Co_variables.txt
turbine_design/Models/Al2a_model_phi_psi_M2_Co/Al2a_model_phi_psi_M2_Co.joblib
turbine_design/Models/Al2a_model_phi_psi_M2_Co/Al2a_model_phi_psi_M2_Co_output_variable.txt
turbine_design/Models/Al2a_model_phi_psi_M2_Co/Al2a_model_phi_psi_M2_Co_variables.txt
turbine_design/Models/Al3_model_phi_psi_M2_Co/Al3_model_phi_psi_M2_Co.joblib
turbine_design-1.1.0.dist-info/METADATA
turbine_design-1.1.0.dist-info/WHEEL
turbine_design-1.1.0.dist-info/RECORD
