Metadata-Version: 2.1
Name: turbine-design
Version: 1.1.0
Summary: A data driven tool for turbine aerodynamic design
Home-page: https://github.com/tom-tyler/turbine_design
License: MIT
Keywords: turbine,turbomachinery,Gaussian
Author: Tom Tyler
Author-email: tom-tyler@outlook.com
Requires-Python: >=3.10,<4.0
Classifier: License :: OSI Approved :: MIT License
Classifier: Programming Language :: Python :: 3
Classifier: Programming Language :: Python :: 3.10
Classifier: Programming Language :: Python :: 3.11
Project-URL: Repository, https://github.com/tom-tyler/turbine_design
